swh/auth/__init__.py
swh/auth/cli.py
swh/auth/keycloak.py
swh/auth/py.typed
swh/auth/pytest_plugin.py
swh/auth/utils.py
swh/auth/django/__init__.py
swh/auth/django/backends.py
swh/auth/django/middlewares.py
swh/auth/django/models.py
swh/auth/django/utils.py
swh/auth/django/views.py
swh/auth/starlette/__init__.py
swh/auth/starlette/backends.py
swh/auth/tests/__init__.py
swh/auth/tests/conftest.py
swh/auth/tests/sample_data.py
swh/auth/tests/test_cli.py
swh/auth/tests/test_keycloak.py
swh/auth/tests/test_utils.py
swh/auth/tests/django/__init__.py
swh/auth/tests/django/django_asserts.py
swh/auth/tests/django/test_backends.py
swh/auth/tests/django/test_drf_bearer_token_auth.py
swh/auth/tests/django/test_middlewares.py
swh/auth/tests/django/test_models.py
swh/auth/tests/django/test_utils.py
swh/auth/tests/django/test_views.py
swh/auth/tests/django/app/__init__.py
swh/auth/tests/django/app/manage.py
swh/auth/tests/django/app/apptest/__init__.py
swh/auth/tests/django/app/apptest/apps.py
swh/auth/tests/django/app/apptest/settings.py
swh/auth/tests/django/app/apptest/urls.py
swh/auth/tests/starlette/__init__.py
swh/auth/tests/starlette/test_backend.py
swh_auth-0.10.1.dist-info/licenses/AUTHORS
swh_auth-0.10.1.dist-info/licenses/LICENSE
swh_auth-0.10.1.dist-info/METADATA
swh_auth-0.10.1.dist-info/WHEEL
swh_auth-0.10.1.dist-info/entry_points.txt
swh_auth-0.10.1.dist-info/top_level.txt
swh_auth-0.10.1.dist-info/RECORD
