Metadata-Version: 2.4
Name: swh.auth
Version: 0.10.1
Summary: Software Heritage authentication utilities
Author-email: Software Heritage developers <swh-devel@inria.fr>
Project-URL: Homepage, https://gitlab.softwareheritage.org/swh/devel/swh-auth
Project-URL: Bug Reports, https://gitlab.softwareheritage.org/swh/devel/swh-auth/-/issues
Project-URL: Funding, https://www.softwareheritage.org/donate
Project-URL: Documentation, https://docs.softwareheritage.org/devel/swh-auth/
Project-URL: Source, https://gitlab.softwareheritage.org/swh/devel/swh-auth.git
Classifier: Programming Language :: Python :: 3
Classifier: Intended Audience :: Developers
Classifier: License :: OSI Approved :: GNU General Public License v3 (GPLv3)
Classifier: Operating System :: OS Independent
Classifier: Development Status :: 3 - Alpha
Requires-Python: >=3.9
License-File: LICENSE
License-File: AUTHORS
Requires-Dist: click
Requires-Dist: python-keycloak>=5.3.1
Requires-Dist: pyyaml
Requires-Dist: swh.core[http]>=0.3
Provides-Extra: django
Requires-Dist: django; extra == "django"
Requires-Dist: djangorestframework; extra == "django"
Requires-Dist: sentry-sdk; extra == "django"
Provides-Extra: starlette
Requires-Dist: starlette; extra == "starlette"
Requires-Dist: httpx; extra == "starlette"
Requires-Dist: aiocache; extra == "starlette"
Provides-Extra: testing
Requires-Dist: django-stubs; extra == "testing"
Requires-Dist: djangorestframework-stubs; extra == "testing"
Requires-Dist: pytest>=8.1; extra == "testing"
Requires-Dist: pytest-django; extra == "testing"
Requires-Dist: pytest-mock; extra == "testing"
Requires-Dist: requests_mock; extra == "testing"
Requires-Dist: swh.core[testing]; extra == "testing"
Requires-Dist: types-click; extra == "testing"
Requires-Dist: types-jwcrypto; extra == "testing"
Requires-Dist: types-pytz; extra == "testing"
Requires-Dist: types-pyyaml; extra == "testing"
Requires-Dist: django; extra == "testing"
Requires-Dist: djangorestframework; extra == "testing"
Requires-Dist: sentry-sdk; extra == "testing"
Requires-Dist: starlette; extra == "testing"
Requires-Dist: httpx; extra == "testing"
Requires-Dist: aiocache; extra == "testing"
Dynamic: license-file
